<?xml version="1.0" encoding="utf-8"?>
<extension version="3.1" type="plugin" group="search">
    <name>plg_search_cnrbuonipasto</name>
    <author>Todaro Giovanni - Consiglio Nazionale delle Ricerche -  Istituto per le Tecnologie Didattiche</author>
    <creationDate>2016-08-31</creationDate>
    <copyright>2016 Todaro Giovanni - Consiglio Nazionale delle Ricerche -  Istituto per le Tecnologie Didattiche</copyright>
    <license>GNU General Public License version 2 or later; see LICENSE.txt</license>
    <authorEmail>giovanni.todaro@itd.cnr.it</authorEmail>
    <authorUrl>http://www.pa.itd.cnr.it</authorUrl>
    <version>CVS: 1.0.0</version>
    <description>PLG_SEARCH_COM_CNRBUONIPASTO_XML_DESCRIPTION</description>
    <files>
        <filename plugin="cnrbuonipasto">cnrbuonipasto.php</filename>
        <filename>index.html</filename>
    </files>
    <languages folder="../../../languages/site/search/cnrbuonipasto">
        
			<language tag="en-GB">../../../languages/plugins/search/cnrbuonipasto/en-GB/en-GB.plg_search_cnrbuonipasto.ini</language>
			<language tag="en-GB">../../../languages/plugins/search/cnrbuonipasto/en-GB/en-GB.plg_search_cnrbuonipasto.sys.ini</language>
			<language tag="it-IT">../../../languages/plugins/search/cnrbuonipasto/it-IT/it-IT.plg_search_cnrbuonipasto.ini</language>
			<language tag="it-IT">../../../languages/plugins/search/cnrbuonipasto/it-IT/it-IT.plg_search_cnrbuonipasto.sys.ini</language>
    </languages>
    <config>
        <fields name="params">

            <fieldset name="basic">
                <field name="search_limit" type="text" default="50" size="5"
                       description="PLG_SEARCH_COM_CNRBUONIPASTO_FIELD_SEARCHLIMIT_DESC"
                       label="PLG_SEARCH_COM_CNRBUONIPASTO_FIELD_SEARCHLIMIT_LABEL" />
            </fieldset>

        </fields>
    </config>
</extension>
